cloudlaunch/__init__.py
cloudlaunch/admin.py
cloudlaunch/apps.py
cloudlaunch/forms.py
cloudlaunch/models.py
cloudlaunch/serializers.py
cloudlaunch/signals.py
cloudlaunch/tasks.py
cloudlaunch/tests.py
cloudlaunch/urls.py
cloudlaunch/util.py
cloudlaunch/view_helpers.py
cloudlaunch/views.py
cloudlaunch/migrations/0001_initial.py
cloudlaunch/migrations/0002_application_display_order.py
cloudlaunch/migrations/0003_deployment_credentials_relationship.py
cloudlaunch/migrations/__init__.py
cloudlaunch_server-2.0.2.dist-info/DESCRIPTION.rst
cloudlaunch_server-2.0.2.dist-info/METADATA
cloudlaunch_server-2.0.2.dist-info/RECORD
cloudlaunch_server-2.0.2.dist-info/WHEEL
cloudlaunch_server-2.0.2.dist-info/entry_points.txt
cloudlaunch_server-2.0.2.dist-info/metadata.json
cloudlaunch_server-2.0.2.dist-info/top_level.txt
cloudlaunchserver/__init__.py
cloudlaunchserver/celery.py
cloudlaunchserver/celeryconfig.py
cloudlaunchserver/settings.py
cloudlaunchserver/settings_local.py
cloudlaunchserver/urls.py
cloudlaunchserver/wsgi.py
cloudlaunchserver/runner/__init__.py
cloudlaunchserver/runner/__main__.py
cloudlaunchserver/runner/decorators.py
cloudlaunchserver/runner/commands/__init__.py
cloudlaunchserver/runner/commands/django.py
cloudlaunchserver/runner/commands/help.py
public_appliances/__init__.py
public_appliances/admin.py
public_appliances/apps.py
public_appliances/models.py
public_appliances/serializers.py
public_appliances/tests.py
public_appliances/urls.py
public_appliances/views.py
public_appliances/migrations/0001_initial.py
public_appliances/migrations/__init__.py
